{
  "year": 2025,
  "month": 4,
  "week": 4,
  "generated_at": "2025-10-17T16:25:00.227823Z",
  "model_version": "da39a3ee5e",
  "data": [
    {
      "province": "ACEH",
      "value": 21400.0
    },
    {
      "province": "BALI",
      "value": 21850.0
    },
    {
      "province": "BANGKA BELITUNG",
      "value": 18457.14285714286
    },
    {
      "province": "BANTEN",
      "value": 19033.333333333332
    },
    {
      "province": "BENGKULU",
      "value": 20050.0
    },
    {
      "province": "DAERAH ISTIMEWA YOGYAKARTA",
      "value": 19650.0
    },
    {
      "province": "DI. ACEH",
      "value": 20650.0
    },
    {
      "province": "DKI JAKARTA",
      "value": 21000.0
    },
    {
      "province": "GORONTALO",
      "value": 25992.85714285714
    },
    {
      "province": "JAMBI",
      "value": 20700.0
    },
    {
      "province": "JAWA BARAT",
      "value": 20853.571428571428
    },
    {
      "province": "JAWA TENGAH",
      "value": 19864.935064935064
    },
    {
      "province": "JAWA TIMUR",
      "value": 20141.428571428572
    },
    {
      "province": "KALIMANTAN BARAT",
      "value": 20450.0
    },
    {
      "province": "KALIMANTAN SELATAN",
      "value": 20978.571428571428
    },
    {
      "province": "KALIMANTAN TENGAH",
      "value": 20914.285714285714
    },
    {
      "province": "KALIMANTAN TIMUR",
      "value": 21340.47619047619
    },
    {
      "province": "KALIMANTAN UTARA",
      "value": 20853.571428571428
    },
    {
      "province": "KEPULAUAN RIAU",
      "value": 19134.285714285714
    },
    {
      "province": "LAMPUNG",
      "value": 20267.85714285714
    },
    {
      "province": "MALUKU",
      "value": 22950.0
    },
    {
      "province": "MALUKU UTARA",
      "value": 21850.0
    },
    {
      "province": "NUSA TENGGARA TIMUR",
      "value": 21878.571428571428
    },
    {
      "province": "PAPUA",
      "value": 23955.714285714286
    },
    {
      "province": "PAPUA BARAT",
      "value": 23764.285714285714
    },
    {
      "province": "SULAWESI BARAT",
      "value": 21085.714285714286
    },
    {
      "province": "SULAWESI SELATAN",
      "value": 19451.428571428572
    },
    {
      "province": "SULAWESI TENGAH",
      "value": 20300.0
    },
    {
      "province": "SULAWESI TENGGARA",
      "value": 21950.0
    },
    {
      "province": "SULAWESI UTARA",
      "value": 18950.0
    },
    {
      "province": "SUMATERA BARAT",
      "value": 19950.0
    },
    {
      "province": "SUMATERA SELATAN",
      "value": 21800.0
    },
    {
      "province": "SUMATERA UTARA",
      "value": 20718.571428571428
    }
  ]
}