{
  "year": 2022,
  "month": 7,
  "week": 1,
  "generated_at": "2025-10-17T16:25:00.227823Z",
  "model_version": "da39a3ee5e",
  "data": [
    {
      "province": "ACEH",
      "value": 17403.571428571428
    },
    {
      "province": "BALI",
      "value": 21100.0
    },
    {
      "province": "BANGKA BELITUNG",
      "value": 21764.285714285714
    },
    {
      "province": "BANTEN",
      "value": 20033.333333333332
    },
    {
      "province": "BENGKULU",
      "value": 22014.285714285714
    },
    {
      "province": "DAERAH ISTIMEWA YOGYAKARTA",
      "value": 19592.85714285714
    },
    {
      "province": "DI. ACEH",
      "value": 21342.85714285714
    },
    {
      "province": "DKI JAKARTA",
      "value": 21700.0
    },
    {
      "province": "GORONTALO",
      "value": 25742.85714285714
    },
    {
      "province": "JAMBI",
      "value": 21164.285714285714
    },
    {
      "province": "JAWA BARAT",
      "value": 20794.64285714286
    },
    {
      "province": "JAWA TENGAH",
      "value": 20258.44155844156
    },
    {
      "province": "JAWA TIMUR",
      "value": 20709.285714285714
    },
    {
      "province": "KALIMANTAN BARAT",
      "value": 21766.666666666668
    },
    {
      "province": "KALIMANTAN SELATAN",
      "value": 22383.333333333332
    },
    {
      "province": "KALIMANTAN TENGAH",
      "value": 23100.0
    },
    {
      "province": "KALIMANTAN TIMUR",
      "value": 22247.619047619046
    },
    {
      "province": "KALIMANTAN UTARA",
      "value": 25185.714285714286
    },
    {
      "province": "KEPULAUAN RIAU",
      "value": 21224.285714285714
    },
    {
      "province": "LAMPUNG",
      "value": 16864.056428571428
    },
    {
      "province": "MALUKU",
      "value": 27639.285714285714
    },
    {
      "province": "MALUKU UTARA",
      "value": 27100.0
    },
    {
      "province": "NUSA TENGGARA TIMUR",
      "value": 24509.183673469386
    },
    {
      "province": "PAPUA",
      "value": 27975.714285714286
    },
    {
      "province": "PAPUA BARAT",
      "value": 30535.714285714286
    },
    {
      "province": "SULAWESI BARAT",
      "value": 22483.333333333332
    },
    {
      "province": "SULAWESI SELATAN",
      "value": 21265.714285714286
    },
    {
      "province": "SULAWESI TENGAH",
      "value": 19721.428571428572
    },
    {
      "province": "SULAWESI TENGGARA",
      "value": 28103.571428571428
    },
    {
      "province": "SULAWESI UTARA",
      "value": 20160.714285714286
    },
    {
      "province": "SUMATERA BARAT",
      "value": 19900.0
    },
    {
      "province": "SUMATERA SELATAN",
      "value": 25750.0
    },
    {
      "province": "SUMATERA UTARA",
      "value": 21078.571428571428
    }
  ]
}