{
  "year": 2023,
  "month": 12,
  "week": 2,
  "generated_at": "2025-10-17T16:25:00.227823Z",
  "model_version": "da39a3ee5e",
  "data": [
    {
      "province": "ACEH",
      "value": 19857.14285714286
    },
    {
      "province": "BALI",
      "value": 19950.0
    },
    {
      "province": "BANGKA BELITUNG",
      "value": 16100.0
    },
    {
      "province": "BANTEN",
      "value": 17616.666666666668
    },
    {
      "province": "BENGKULU",
      "value": 17007.14285714286
    },
    {
      "province": "DAERAH ISTIMEWA YOGYAKARTA",
      "value": 16792.85714285714
    },
    {
      "province": "DI. ACEH",
      "value": 17700.0
    },
    {
      "province": "DKI JAKARTA",
      "value": 18150.0
    },
    {
      "province": "GORONTALO",
      "value": 22678.571428571428
    },
    {
      "province": "JAMBI",
      "value": 17550.0
    },
    {
      "province": "JAWA BARAT",
      "value": 17860.714285714286
    },
    {
      "province": "JAWA TENGAH",
      "value": 17725.974025974025
    },
    {
      "province": "JAWA TIMUR",
      "value": 17545.714285714286
    },
    {
      "province": "KALIMANTAN BARAT",
      "value": 18533.333333333332
    },
    {
      "province": "KALIMANTAN SELATAN",
      "value": 19516.666666666668
    },
    {
      "province": "KALIMANTAN TENGAH",
      "value": 19750.0
    },
    {
      "province": "KALIMANTAN TIMUR",
      "value": 19807.14285714286
    },
    {
      "province": "KALIMANTAN UTARA",
      "value": 20225.0
    },
    {
      "province": "KEPULAUAN RIAU",
      "value": 16210.0
    },
    {
      "province": "LAMPUNG",
      "value": 14885.486428571428
    },
    {
      "province": "MALUKU",
      "value": 21200.0
    },
    {
      "province": "MALUKU UTARA",
      "value": 21300.0
    },
    {
      "province": "NUSA TENGGARA TIMUR",
      "value": 19706.122448979593
    },
    {
      "province": "PAPUA",
      "value": 23184.285714285714
    },
    {
      "province": "PAPUA BARAT",
      "value": 23810.714285714286
    },
    {
      "province": "SULAWESI BARAT",
      "value": 19566.666666666668
    },
    {
      "province": "SULAWESI SELATAN",
      "value": 17990.0
    },
    {
      "province": "SULAWESI TENGAH",
      "value": 17850.0
    },
    {
      "province": "SULAWESI TENGGARA",
      "value": 21100.0
    },
    {
      "province": "SULAWESI UTARA",
      "value": 16628.571428571428
    },
    {
      "province": "SUMATERA BARAT",
      "value": 16628.571428571428
    },
    {
      "province": "SUMATERA SELATAN",
      "value": 21500.0
    },
    {
      "province": "SUMATERA UTARA",
      "value": 17888.571428571428
    }
  ]
}